ScraperSage/__init__.py
ScraperSage/ai_providers.py
ScraperSage/scraper_sage.py
scrapersage-1.2.2.dist-info/licenses/LICENSE
scrapersage-1.2.2.dist-info/METADATA
scrapersage-1.2.2.dist-info/WHEEL
scrapersage-1.2.2.dist-info/entry_points.txt
scrapersage-1.2.2.dist-info/top_level.txt
scrapersage-1.2.2.dist-info/RECORD
