Metadata-Version: 2.4
Name: ScraperSage
Version: 1.2.2
Summary: A comprehensive web scraping and content summarization library with explicit AI provider and model selection (Gemini, OpenAI, OpenRouter, DeepSeek)
Home-page: https://github.com/akillabs/ScraperSage
Author: Akil
Author-email: Akil <akil@example.com>
License: MIT
Project-URL: Homepage, https://github.com/akil/ScraperSage
Project-URL: Bug Reports, https://github.com/akil/ScraperSage/issues
Project-URL: Source, https://github.com/akil/ScraperSage
Project-URL: Documentation, https://github.com/akil/ScraperSage/blob/main/README.md
Keywords: web scraping,content summarization,search,AI,playwright,gemini,openai,openrouter,deepseek
Classifier: Development Status :: 4 - Beta
Classifier: Intended Audience :: Developers
Classifier: Topic :: Software Development :: Libraries :: Python Modules
Classifier: Topic :: Internet :: WWW/HTTP :: Indexing/Search
Classifier: Topic :: Scientific/Engineering :: Artificial Intelligence
Classifier: License :: OSI Approved :: MIT License
Classifier: Programming Language :: Python :: 3
Classifier: Programming Language :: Python :: 3.8
Classifier: Programming Language :: Python :: 3.9
Classifier: Programming Language :: Python :: 3.10
Classifier: Programming Language :: Python :: 3.11
Classifier: Programming Language :: Python :: 3.12
Requires-Python: >=3.8
License-File: LICENSE
Requires-Dist: requests
Requires-Dist: ddgs
Requires-Dist: playwright
Requires-Dist: google-generativeai
Requires-Dist: openai
Requires-Dist: beautifulsoup4
Requires-Dist: tenacity
Requires-Dist: httpx
Provides-Extra: dev
Requires-Dist: pytest>=6.0; extra == "dev"
Requires-Dist: pytest-asyncio; extra == "dev"
Requires-Dist: black; extra == "dev"
Requires-Dist: flake8; extra == "dev"
Requires-Dist: mypy; extra == "dev"
Dynamic: author
Dynamic: home-page
Dynamic: license-file
Dynamic: requires-python
